{
  "status": "ok",
  "label": "tracked_queries",
  "rows": [
    {
      "queryid": "6416750758406621842",
      "calls": 38417,
      "total_ms": "82898400.68",
      "mean_ms": "2157.86"
    },
    {
      "queryid": "-5344960703026327435",
      "calls": 6691,
      "total_ms": "14146203.89",
      "mean_ms": "2114.21"
    },
    {
      "queryid": "-6712128630152386476",
      "calls": 5106,
      "total_ms": "9985405.38",
      "mean_ms": "1955.62"
    },
    {
      "queryid": "-225245605736690330",
      "calls": 3216,
      "total_ms": "4192966.80",
      "mean_ms": "1303.78"
    },
    {
      "queryid": "-5044213774447814878",
      "calls": 3056,
      "total_ms": "3907298.51",
      "mean_ms": "1278.57"
    },
    {
      "queryid": "-2876120296317350531",
      "calls": 612039,
      "total_ms": "3832695.82",
      "mean_ms": "6.26"
    },
    {
      "queryid": "-922008049376959953",
      "calls": 2257,
      "total_ms": "2638989.76",
      "mean_ms": "1169.25"
    },
    {
      "queryid": "852176900607336119",
      "calls": 2259,
      "total_ms": "2638492.51",
      "mean_ms": "1167.99"
    },
    {
      "queryid": "2744925251257801673",
      "calls": 893,
      "total_ms": "1906495.19",
      "mean_ms": "2134.93"
    },
    {
      "queryid": "-5633448213020496946",
      "calls": 152,
      "total_ms": "1017181.23",
      "mean_ms": "6691.98"
    },
    {
      "queryid": "8277935260341689633",
      "calls": 121,
      "total_ms": "686606.34",
      "mean_ms": "5674.43"
    },
    {
      "queryid": "-922008049376959953",
      "calls": 2,
      "total_ms": "0.04",
      "mean_ms": "0.02"
    }
  ]
}